<annotation verified="yes">
	<folder>ImageSets2</folder>
	<filename>91.png</filename>
	<path>/mnt/data/talha/Finetuning/Table extraction/mmdetection_object_detection_demo/data/VOC2007/ImageSets2/91.png</path>
	<source>
		<database>Unknown</database>
	</source>
	<size>
		<width>1270</width>
		<height>1642</height>
		<depth>3</depth>
	</size>
	<segmented>0</segmented>
	<object>
		<name>data</name>
		<pose>Unspecified</pose>
		<truncated>0</truncated>
		<difficult>0</difficult>
		<bndbox>
			<xmin>728</xmin>
			<ymin>118</ymin>
			<xmax>1168</xmax>
			<ymax>270</ymax>
		</bndbox>
	</object>
	<object>
		<name>data</name>
		<pose>Unspecified</pose>
		<truncated>0</truncated>
		<difficult>0</difficult>
		<bndbox>
			<xmin>53</xmin>
			<ymin>116</ymin>
			<xmax>328</xmax>
			<ymax>345</ymax>
		</bndbox>
	</object>
	<object>
		<name>table</name>
		<pose>Unspecified</pose>
		<truncated>0</truncated>
		<difficult>0</difficult>
		<bndbox>
			<xmin>52</xmin>
			<ymin>515</ymin>
			<xmax>1236</xmax>
			<ymax>595</ymax>
		</bndbox>
	</object>
	<object>
		<name>table</name>
		<pose>Unspecified</pose>
		<truncated>0</truncated>
		<difficult>0</difficult>
		<bndbox>
			<xmin>55</xmin>
			<ymin>654</ymin>
			<xmax>1121</xmax>
			<ymax>847</ymax>
		</bndbox>
	</object>
</annotation>
